aliyunsdkdms_dg/__init__.py
aliyunsdkdms_dg/request/__init__.py
aliyunsdkdms_dg/request/v20230914/AddDatabaseListRequest.py
aliyunsdkdms_dg/request/v20230914/AddDatabaseRequest.py
aliyunsdkdms_dg/request/v20230914/CheckDGEnabledRequest.py
aliyunsdkdms_dg/request/v20230914/ConnectDatabaseRequest.py
aliyunsdkdms_dg/request/v20230914/CreateGatewayRequest.py
aliyunsdkdms_dg/request/v20230914/CreateGatewayVerifyCodeRequest.py
aliyunsdkdms_dg/request/v20230914/DeleteDatabaseRequest.py
aliyunsdkdms_dg/request/v20230914/DeleteGatewayInstanceRequest.py
aliyunsdkdms_dg/request/v20230914/DeleteGatewayRequest.py
aliyunsdkdms_dg/request/v20230914/DescribeRegionsRequest.py
aliyunsdkdms_dg/request/v20230914/DownloadGatewayProgramRequest.py
aliyunsdkdms_dg/request/v20230914/FindUserGatewayByIdRequest.py
aliyunsdkdms_dg/request/v20230914/GetUserDatabasesRequest.py
aliyunsdkdms_dg/request/v20230914/GetUserGatewayInstancesRequest.py
aliyunsdkdms_dg/request/v20230914/GetUserGatewaysRequest.py
aliyunsdkdms_dg/request/v20230914/ListDatabaseAccessPointRequest.py
aliyunsdkdms_dg/request/v20230914/ModifyDatabaseRequest.py
aliyunsdkdms_dg/request/v20230914/ModifyGatewayRequest.py
aliyunsdkdms_dg/request/v20230914/RetryDatabaseRequest.py
aliyunsdkdms_dg/request/v20230914/StopGatewayRequest.py
aliyunsdkdms_dg/request/v20230914/__init__.py
aliyun_python_sdk_dms_dg-1.0.0.dist-info/LICENSE
aliyun_python_sdk_dms_dg-1.0.0.dist-info/METADATA
aliyun_python_sdk_dms_dg-1.0.0.dist-info/WHEEL
aliyun_python_sdk_dms_dg-1.0.0.dist-info/top_level.txt
aliyun_python_sdk_dms_dg-1.0.0.dist-info/RECORD
